odoo/addons/internal_stock_quant_package/README.rst
odoo/addons/internal_stock_quant_package/__init__.py
odoo/addons/internal_stock_quant_package/__manifest__.py
odoo/addons/internal_stock_quant_package/i18n/fr_BE.po
odoo/addons/internal_stock_quant_package/i18n/internal_stock_quant_package.pot
odoo/addons/internal_stock_quant_package/i18n/it.po
odoo/addons/internal_stock_quant_package/models/__init__.py
odoo/addons/internal_stock_quant_package/models/stock_internal_package_config_line.py
odoo/addons/internal_stock_quant_package/models/stock_picking.py
odoo/addons/internal_stock_quant_package/models/stock_picking_type.py
odoo/addons/internal_stock_quant_package/models/stock_quant_package.py
odoo/addons/internal_stock_quant_package/readme/CONTRIBUTORS.md
odoo/addons/internal_stock_quant_package/readme/DESCRIPTION.md
odoo/addons/internal_stock_quant_package/readme/USAGE.md
odoo/addons/internal_stock_quant_package/security/ir.model.access.csv
odoo/addons/internal_stock_quant_package/static/description/icon.png
odoo/addons/internal_stock_quant_package/static/description/index.html
odoo/addons/internal_stock_quant_package/tests/__init__.py
odoo/addons/internal_stock_quant_package/tests/common.py
odoo/addons/internal_stock_quant_package/tests/test_stock_picking.py
odoo/addons/internal_stock_quant_package/tests/test_stock_quant_package.py
odoo/addons/internal_stock_quant_package/views/stock_picking_type_views.xml
odoo/addons/internal_stock_quant_package/views/stock_quant_package_views.xml
odoo_addon_internal_stock_quant_package-18.0.1.1.0.dist-info/METADATA
odoo_addon_internal_stock_quant_package-18.0.1.1.0.dist-info/WHEEL
odoo_addon_internal_stock_quant_package-18.0.1.1.0.dist-info/top_level.txt
odoo_addon_internal_stock_quant_package-18.0.1.1.0.dist-info/RECORD
