Metadata-Version: 2.1
Name: odoo-addon-internal_stock_quant_package
Version: 18.0.1.1.0
Requires-Python: >=3.10
Requires-Dist: odoo-addon-delivery_procurement_group_carrier==18.0.*
Requires-Dist: odoo==18.0.*
Summary: This module allows to declare internal stock quant package
Home-page: https://github.com/OCA/stock-logistics-tracking
License: AGPL-3
Author: ACSONE SA/NV, Odoo Community Association (OCA)
Author-email: support@odoo-community.org
Classifier: Programming Language :: Python
Classifier: Framework :: Odoo
Classifier: Framework :: Odoo :: 18.0
Classifier: License :: OSI Approved :: GNU Affero General Public License v3
